<?xml version="1.0" encoding="utf-8" ?>
<dwsync>
<file name="SegmentMembershipContext.php" server="ftp.mynyte.co.uk//public_html/staging/" local="131523769140000000" remote="131528050800000000" Dst="2" />
<file name="SegmentMembershipList.php" server="ftp.mynyte.co.uk//public_html/staging/" local="131523769140000000" remote="131528050800000000" Dst="2" />
<file name="SegmentMembershipPage.php" server="ftp.mynyte.co.uk//public_html/staging/" local="131523769140000000" remote="131528050800000000" Dst="2" />
<file name="UserBindingContext.php" server="ftp.mynyte.co.uk//public_html/staging/" local="131523769140000000" remote="131528050800000000" Dst="2" />
<file name="SegmentMembershipInstance.php" server="ftp.mynyte.co.uk//public_html/staging/" local="131523769140000000" remote="131528050800000000" Dst="2" />
<file name="UserBindingList.php" server="ftp.mynyte.co.uk//public_html/staging/" local="131523769140000000" remote="131528050800000000" Dst="2" />
<file name="UserBindingOptions.php" server="ftp.mynyte.co.uk//public_html/staging/" local="131523769140000000" remote="131528050800000000" Dst="2" />
<file name="UserBindingInstance.php" server="ftp.mynyte.co.uk//public_html/staging/" local="131523769140000000" remote="131528050800000000" Dst="2" />
<file name="UserBindingPage.php" server="ftp.mynyte.co.uk//public_html/staging/" local="131523769140000000" remote="131528050800000000" Dst="2" />
<file name="SegmentMembershipContext.php" server="ftp.mynyte.co.uk//public_html/live/" local="131528121140779940" remote="131528123400000000" Dst="2" />
<file name="SegmentMembershipList.php" server="ftp.mynyte.co.uk//public_html/live/" local="131528121140789949" remote="131528123400000000" Dst="2" />
<file name="SegmentMembershipInstance.php" server="ftp.mynyte.co.uk//public_html/live/" local="131528121140779940" remote="131528123400000000" Dst="2" />
<file name="SegmentMembershipPage.php" server="ftp.mynyte.co.uk//public_html/live/" local="131528121140789949" remote="131528123400000000" Dst="2" />
<file name="UserBindingContext.php" server="ftp.mynyte.co.uk//public_html/live/" local="131528121140799959" remote="131528123400000000" Dst="2" />
<file name="UserBindingInstance.php" server="ftp.mynyte.co.uk//public_html/live/" local="131528121140799959" remote="131528123400000000" Dst="2" />
<file name="UserBindingList.php" server="ftp.mynyte.co.uk//public_html/live/" local="131528121140809965" remote="131528123400000000" Dst="2" />
<file name="UserBindingOptions.php" server="ftp.mynyte.co.uk//public_html/live/" local="131528121140819975" remote="131528123400000000" Dst="2" />
<file name="UserBindingPage.php" server="ftp.mynyte.co.uk//public_html/live/" local="131528121140819975" remote="131528123400000000" Dst="2" />
</dwsync>