<?xml version="1.0" encoding="utf-8" ?>
<dwsync>
<file name="TaskQueueCumulativeStatisticsContext.php" server="ftp.mynyte.co.uk//public_html/staging/" local="131523769140000000" remote="131528051400000000" Dst="2" />
<file name="TaskQueueCumulativeStatisticsList.php" server="ftp.mynyte.co.uk//public_html/staging/" local="131523769140000000" remote="131528051400000000" Dst="2" />
<file name="TaskQueueCumulativeStatisticsOptions.php" server="ftp.mynyte.co.uk//public_html/staging/" local="131523769140000000" remote="131528051400000000" Dst="2" />
<file name="TaskQueueCumulativeStatisticsPage.php" server="ftp.mynyte.co.uk//public_html/staging/" local="131523769140000000" remote="131528051400000000" Dst="2" />
<file name="TaskQueueRealTimeStatisticsContext.php" server="ftp.mynyte.co.uk//public_html/staging/" local="131523769140000000" remote="131528051400000000" Dst="2" />
<file name="TaskQueueRealTimeStatisticsInstance.php" server="ftp.mynyte.co.uk//public_html/staging/" local="131523769140000000" remote="131528051400000000" Dst="2" />
<file name="TaskQueueCumulativeStatisticsInstance.php" server="ftp.mynyte.co.uk//public_html/staging/" local="131523769140000000" remote="131528051400000000" Dst="2" />
<file name="TaskQueueRealTimeStatisticsList.php" server="ftp.mynyte.co.uk//public_html/staging/" local="131523769140000000" remote="131528051400000000" Dst="2" />
<file name="TaskQueueRealTimeStatisticsOptions.php" server="ftp.mynyte.co.uk//public_html/staging/" local="131523769140000000" remote="131528051400000000" Dst="2" />
<file name="TaskQueueRealTimeStatisticsPage.php" server="ftp.mynyte.co.uk//public_html/staging/" local="131523769140000000" remote="131528051400000000" Dst="2" />
<file name="TaskQueuesStatisticsInstance.php" server="ftp.mynyte.co.uk//public_html/staging/" local="131523769140000000" remote="131528051400000000" Dst="2" />
<file name="TaskQueuesStatisticsList.php" server="ftp.mynyte.co.uk//public_html/staging/" local="131523769140000000" remote="131528051400000000" Dst="2" />
<file name="TaskQueuesStatisticsOptions.php" server="ftp.mynyte.co.uk//public_html/staging/" local="131523769140000000" remote="131528051400000000" Dst="2" />
<file name="TaskQueuesStatisticsPage.php" server="ftp.mynyte.co.uk//public_html/staging/" local="131523769140000000" remote="131528051400000000" Dst="2" />
<file name="TaskQueueStatisticsContext.php" server="ftp.mynyte.co.uk//public_html/staging/" local="131523769140000000" remote="131528051400000000" Dst="2" />
<file name="TaskQueueStatisticsInstance.php" server="ftp.mynyte.co.uk//public_html/staging/" local="131523769140000000" remote="131528051400000000" Dst="2" />
<file name="TaskQueueStatisticsList.php" server="ftp.mynyte.co.uk//public_html/staging/" local="131523769140000000" remote="131528051400000000" Dst="2" />
<file name="TaskQueueStatisticsOptions.php" server="ftp.mynyte.co.uk//public_html/staging/" local="131523769140000000" remote="131528051400000000" Dst="2" />
<file name="TaskQueueStatisticsPage.php" server="ftp.mynyte.co.uk//public_html/staging/" local="131523769140000000" remote="131528051400000000" Dst="2" />
<file name="TaskQueueCumulativeStatisticsContext.php" server="ftp.mynyte.co.uk//public_html/live/" local="131528121142938052" remote="131528123400000000" Dst="2" />
<file name="TaskQueueCumulativeStatisticsInstance.php" server="ftp.mynyte.co.uk//public_html/live/" local="131528121142938052" remote="131528123400000000" Dst="2" />
<file name="TaskQueueCumulativeStatisticsList.php" server="ftp.mynyte.co.uk//public_html/live/" local="131528121142938052" remote="131528123400000000" Dst="2" />
<file name="TaskQueueCumulativeStatisticsOptions.php" server="ftp.mynyte.co.uk//public_html/live/" local="131528121142938052" remote="131528123400000000" Dst="2" />
<file name="TaskQueueCumulativeStatisticsPage.php" server="ftp.mynyte.co.uk//public_html/live/" local="131528121142938052" remote="131528123400000000" Dst="2" />
<file name="TaskQueueRealTimeStatisticsContext.php" server="ftp.mynyte.co.uk//public_html/live/" local="131528121142938052" remote="131528123400000000" Dst="2" />
<file name="TaskQueueRealTimeStatisticsInstance.php" server="ftp.mynyte.co.uk//public_html/live/" local="131528121142938052" remote="131528123400000000" Dst="2" />
<file name="TaskQueueRealTimeStatisticsList.php" server="ftp.mynyte.co.uk//public_html/live/" local="131528121142938052" remote="131528123400000000" Dst="2" />
<file name="TaskQueueRealTimeStatisticsOptions.php" server="ftp.mynyte.co.uk//public_html/live/" local="131528121142938052" remote="131528123400000000" Dst="2" />
<file name="TaskQueueRealTimeStatisticsPage.php" server="ftp.mynyte.co.uk//public_html/live/" local="131528121142938052" remote="131528123400000000" Dst="2" />
<file name="TaskQueuesStatisticsInstance.php" server="ftp.mynyte.co.uk//public_html/live/" local="131528121142938052" remote="131528123400000000" Dst="2" />
<file name="TaskQueuesStatisticsList.php" server="ftp.mynyte.co.uk//public_html/live/" local="131528121142938052" remote="131528123400000000" Dst="2" />
<file name="TaskQueuesStatisticsPage.php" server="ftp.mynyte.co.uk//public_html/live/" local="131528121142938052" remote="131528123400000000" Dst="2" />
<file name="TaskQueueStatisticsContext.php" server="ftp.mynyte.co.uk//public_html/live/" local="131528121142938052" remote="131528123400000000" Dst="2" />
<file name="TaskQueuesStatisticsOptions.php" server="ftp.mynyte.co.uk//public_html/live/" local="131528121142938052" remote="131528123400000000" Dst="2" />
<file name="TaskQueueStatisticsInstance.php" server="ftp.mynyte.co.uk//public_html/live/" local="131528121142938052" remote="131528123400000000" Dst="2" />
<file name="TaskQueueStatisticsList.php" server="ftp.mynyte.co.uk//public_html/live/" local="131528121142938052" remote="131528123400000000" Dst="2" />
<file name="TaskQueueStatisticsOptions.php" server="ftp.mynyte.co.uk//public_html/live/" local="131528121142938052" remote="131528123400000000" Dst="2" />
<file name="TaskQueueStatisticsPage.php" server="ftp.mynyte.co.uk//public_html/live/" local="131528121142938052" remote="131528123400000000" Dst="2" />
</dwsync>